{
	"groups": [
		{
			"keys": "bg_jpg,egret_icon_png,description_json,person_json,person_png",
			"name": "preload"
		}
	],
	"resources": [
		{
			"name": "bg_jpg",
			"type": "image",
			"url": "assets/bg.jpg"
		},
		{
			"name": "egret_icon_png",
			"type": "image",
			"url": "assets/egret_icon.png"
		},
		{
			"name": "description_json",
			"type": "json",
			"url": "config/description.json"
		},
		{
			"name": "person_json",
			"type": "json",
			"url": "assets/person.json"
		},
		{
			"name": "person_png",
			"type": "image",
			"url": "assets/person.png"
		}
	]
}